ibei/__init__.py
ibei/_version.py
ibei/models.py
ibei-2.0.4.dist-info/METADATA
ibei-2.0.4.dist-info/WHEEL
ibei-2.0.4.dist-info/licenses/LICENSE
ibei-2.0.4.dist-info/RECORD
