Metadata-Version: 2.4
Name: ibei
Version: 2.0.4
Summary: Calculator for incomplete Bose-Einstein integral
Project-URL: Documentation, https://ibei.readthedocs.io/en/latest/
Project-URL: Issues, https://github.com/jrsmith3/ibei/issues
Project-URL: Source, https://github.com/jrsmith3/ibei
Author-email: Joshua Ryan Smith <joshua.r.smith@gmail.com>
License-Expression: MIT
License-File: LICENSE
Keywords: Bose-Einstein integral,Bose-Einstein statistics,thermal radiation
Classifier: Development Status :: 5 - Production/Stable
Classifier: Intended Audience :: Science/Research
Classifier: License :: OSI Approved :: MIT License
Classifier: Natural Language :: English
Classifier: Operating System :: OS Independent
Classifier: Programming Language :: Python
Classifier: Programming Language :: Python :: 3.10
Classifier: Topic :: Scientific/Engineering :: Physics
Requires-Python: >=3.10
Requires-Dist: astropy
Requires-Dist: attrs
Requires-Dist: mpmath
Requires-Dist: numpy>=1.26.4
